ontologia/README.md
ontologia/__init__.py
ontologia/_compat.py
ontologia/bootstrap.py
ontologia/config.py
ontologia/metrics.py
ontologia/tracing.py
ontologia/validators.py
ontologia/warnings_config.py
ontologia/actions/__init__.py
ontologia/actions/exceptions.py
ontologia/actions/registry.py
ontologia/actions/system_actions.py
ontologia/actions/test_actions.py
ontologia/actions/temporal/__init__.py
ontologia/actions/temporal/activities.py
ontologia/actions/temporal/workflows.py
ontologia/application/__init__.py
ontologia/application/actions_service.py
ontologia/application/analytics_service.py
ontologia/application/change_set_service.py
ontologia/application/data_analysis_service.py
ontologia/application/datacatalog_service.py
ontologia/application/instances_service.py
ontologia/application/linked_objects_service.py
ontologia/application/metamodel_service.py
ontologia/application/migration_execution_service.py
ontologia/application/policy_service.py
ontologia/application/schema_evolution_service.py
ontologia/application/settings.py
ontologia/application/simplified_settings.py
ontologia/application/sync_service.py
ontologia/dependencies/__init__.py
ontologia/dependencies/factories.py
ontologia/dependencies/service_providers.py
ontologia/domain/events.py
ontologia/domain/change_sets/__init__.py
ontologia/domain/change_sets/models_sql.py
ontologia/domain/instances/__init__.py
ontologia/domain/instances/events.py
ontologia/domain/instances/repositories.py
ontologia/domain/metamodels/repositories.py
ontologia/domain/metamodels/value_objects.py
ontologia/domain/metamodels/aggregates/__init__.py
ontologia/domain/metamodels/aggregates/link.py
ontologia/domain/metamodels/aggregates/object_type.py
ontologia/domain/metamodels/instances/dtos.py
ontologia/domain/metamodels/instances/linked_object.py
ontologia/domain/metamodels/instances/models_sql.py
ontologia/domain/metamodels/instances/object.py
ontologia/domain/metamodels/instances/object_instance.py
ontologia-1.7.3.dist-info/METADATA
ontologia-1.7.3.dist-info/WHEEL
ontologia-1.7.3.dist-info/entry_points.txt
ontologia-1.7.3.dist-info/RECORD
