Metadata-Version: 2.4
Name: ontologia
Version: 1.7.3
Summary: An ontology management system built on Registro and SQLModel
Project-URL: Homepage, https://github.com/kevinqz/ontologia
Project-URL: Repository, https://github.com/kevinqz/ontologia
Project-URL: Issues, https://github.com/kevinqz/ontologia/issues
Author-email: Kevin Saltarelli <kevinqz@gmail.com>
License: MIT
Classifier: Development Status :: 4 - Beta
Classifier: Intended Audience :: Developers
Classifier: License :: OSI Approved :: MIT License
Classifier: Programming Language :: Python :: 3
Classifier: Programming Language :: Python :: 3.11
Classifier: Topic :: Software Development :: Libraries :: Python Modules
Requires-Python: >=3.11
Requires-Dist: duckdb>=1.4.1
Requires-Dist: elasticsearch>=8.0.0
Requires-Dist: fastapi>=0.118.0
Requires-Dist: gitpython>=3.1.0
Requires-Dist: httpx>=0.28.1
Requires-Dist: jinja2>=3.1.0
Requires-Dist: kuzu>=0.11.3
Requires-Dist: marimo>=0.17.2
Requires-Dist: matplotlib>=3.10.7
Requires-Dist: networkx>=3.5
Requires-Dist: openpyxl>=3.1.5
Requires-Dist: pandas>=2.3.3
Requires-Dist: plotly>=6.3.1
Requires-Dist: prometheus-client>=0.19.0
Requires-Dist: psutil>=7.1.0
Requires-Dist: pyarrow>=22.0.0
Requires-Dist: pydantic-settings>=2.3.0
Requires-Dist: pydantic>=2.0.0
Requires-Dist: pytest-benchmark>=5.1.0
Requires-Dist: python-jose[cryptography]>=3.3.0
Requires-Dist: python-multipart>=0.0.6
Requires-Dist: pyyaml>=6.0.0
Requires-Dist: pyzmq>=27.1.0
Requires-Dist: questionary>=2.0.1
Requires-Dist: redis>=7.0.0
Requires-Dist: registro>=0.2.2
Requires-Dist: requests>=2.32.5
Requires-Dist: rich>=13.7.0
Requires-Dist: sqlmodel>=0.0.24
Requires-Dist: typer>=0.12.0
Requires-Dist: ulid-py>=1.1.0
Provides-Extra: analytics
Requires-Dist: dbt-duckdb>=1.8.0; extra == 'analytics'
Requires-Dist: duckdb>=1.0.0; extra == 'analytics'
Requires-Dist: polars>=0.20.0; extra == 'analytics'
Provides-Extra: core
Requires-Dist: fastapi>=0.118.0; extra == 'core'
Requires-Dist: gitpython>=3.1.0; extra == 'core'
Requires-Dist: httpx>=0.28.1; extra == 'core'
Requires-Dist: jinja2>=3.1.0; extra == 'core'
Requires-Dist: pydantic-settings>=2.3.0; extra == 'core'
Requires-Dist: pydantic>=2.0.0; extra == 'core'
Requires-Dist: python-jose[cryptography]>=3.3.0; extra == 'core'
Requires-Dist: python-multipart>=0.0.6; extra == 'core'
Requires-Dist: pyyaml>=6.0.0; extra == 'core'
Requires-Dist: questionary>=2.0.1; extra == 'core'
Requires-Dist: registro>=0.2.2; extra == 'core'
Requires-Dist: rich>=13.7.0; extra == 'core'
Requires-Dist: sqlmodel>=0.0.24; extra == 'core'
Requires-Dist: typer>=0.12.0; extra == 'core'
Requires-Dist: ulid-py>=1.1.0; extra == 'core'
Provides-Extra: dev
Requires-Dist: black>=23.3.0; extra == 'dev'
Requires-Dist: dbt-duckdb>=1.8.0; extra == 'dev'
Requires-Dist: duckdb>=1.0.0; extra == 'dev'
Requires-Dist: factory-boy>=3.3.0; extra == 'dev'
Requires-Dist: faker>=19.0.0; extra == 'dev'
Requires-Dist: grpcio-tools>=1.65.0; extra == 'dev'
Requires-Dist: hypothesis>=6.100; extra == 'dev'
Requires-Dist: mkdocs-material>=9.5.0; extra == 'dev'
Requires-Dist: mkdocs>=1.5.0; extra == 'dev'
Requires-Dist: mypy>=1.3.0; extra == 'dev'
Requires-Dist: playwright>=1.40.0; extra == 'dev'
Requires-Dist: pre-commit>=3.7.0; extra == 'dev'
Requires-Dist: pymdown-extensions>=10.0.0; extra == 'dev'
Requires-Dist: pytest-asyncio>=0.21.0; extra == 'dev'
Requires-Dist: pytest-benchmark>=4.0.0; extra == 'dev'
Requires-Dist: pytest-cov>=4.1.0; extra == 'dev'
Requires-Dist: pytest-mock>=3.10.0; extra == 'dev'
Requires-Dist: pytest-profiling>=1.7.0; extra == 'dev'
Requires-Dist: pytest-timeout>=2.1.0; extra == 'dev'
Requires-Dist: pytest-xdist>=3.3.0; extra == 'dev'
Requires-Dist: pytest>=7.0.0; extra == 'dev'
Requires-Dist: redis>=5.0.0; extra == 'dev'
Requires-Dist: requests>=2.31.0; extra == 'dev'
Requires-Dist: ruff>=0.0.272; extra == 'dev'
Requires-Dist: schemathesis>=3.18.4; extra == 'dev'
Requires-Dist: ty>=0.0.1a22; extra == 'dev'
Provides-Extra: edge
Requires-Dist: cbor2>=5.6.0; extra == 'edge'
Requires-Dist: confluent-kafka>=2.5.0; extra == 'edge'
Requires-Dist: cryptography>=41.0.0; extra == 'edge'
Requires-Dist: ecdsa>=0.18.0; extra == 'edge'
Requires-Dist: nats-py>=2.7.0; extra == 'edge'
Requires-Dist: opentelemetry-exporter-otlp>=1.25.0; extra == 'edge'
Requires-Dist: opentelemetry-instrumentation-fastapi>=0.46b0; extra == 'edge'
Requires-Dist: opentelemetry-instrumentation-requests>=0.46b0; extra == 'edge'
Requires-Dist: opentelemetry-sdk>=1.25.0; extra == 'edge'
Requires-Dist: pynacl>=1.5.0; extra == 'edge'
Requires-Dist: redis>=5.0.0; extra == 'edge'
Provides-Extra: full
Requires-Dist: cbor2>=5.6.0; extra == 'full'
Requires-Dist: confluent-kafka>=2.5.0; extra == 'full'
Requires-Dist: cryptography>=41.0.0; extra == 'full'
Requires-Dist: dagster-dbt>=0.23.0; extra == 'full'
Requires-Dist: dagster>=1.7.0; extra == 'full'
Requires-Dist: dbt-duckdb>=1.8.0; extra == 'full'
Requires-Dist: duckdb>=1.0.0; extra == 'full'
Requires-Dist: ecdsa>=0.18.0; extra == 'full'
Requires-Dist: elasticsearch>=8.0.0; extra == 'full'
Requires-Dist: fastmcp>=0.1.0; extra == 'full'
Requires-Dist: grpcio>=1.65.0; extra == 'full'
Requires-Dist: kuzu>=0.5.0; extra == 'full'
Requires-Dist: nats-py>=2.7.0; extra == 'full'
Requires-Dist: opentelemetry-exporter-otlp>=1.25.0; extra == 'full'
Requires-Dist: opentelemetry-instrumentation-fastapi>=0.46b0; extra == 'full'
Requires-Dist: opentelemetry-instrumentation-requests>=0.46b0; extra == 'full'
Requires-Dist: opentelemetry-sdk>=1.25.0; extra == 'full'
Requires-Dist: polars>=0.20.0; extra == 'full'
Requires-Dist: protobuf>=4.25.0; extra == 'full'
Requires-Dist: pynacl>=1.5.0; extra == 'full'
Requires-Dist: redis>=5.0.0; extra == 'full'
Requires-Dist: temporalio>=1.7.0; extra == 'full'
Provides-Extra: graph
Requires-Dist: kuzu>=0.5.0; extra == 'graph'
Provides-Extra: mcp
Requires-Dist: fastmcp>=0.1.0; extra == 'mcp'
Provides-Extra: orchestration
Requires-Dist: dagster-dbt>=0.23.0; extra == 'orchestration'
Requires-Dist: dagster>=1.7.0; extra == 'orchestration'
Provides-Extra: realtime
Requires-Dist: confluent-kafka>=2.5.0; extra == 'realtime'
Requires-Dist: nats-py>=2.7.0; extra == 'realtime'
Provides-Extra: search
Requires-Dist: elasticsearch>=8.0.0; extra == 'search'
Provides-Extra: workflows
Requires-Dist: grpcio>=1.65.0; extra == 'workflows'
Requires-Dist: protobuf>=4.25.0; extra == 'workflows'
Requires-Dist: temporalio>=1.7.0; extra == 'workflows'
